{
    "success": true,
    "data":[{
            "id":7,
            "title": "张爱玲经典语录",
            "desc": "1、世上有用的人往往都是俗人。 2、正经女人虽然痛恨荡妇，其实若有机会 扮个妖妇角色的话，没有一个不跃跃欲试的。 3、完美的女人比完美的男人更完...",
            "imgUrl": " https://upload-images.jianshu.io/upload_images/16572117-9777cb5c4c862d71.jpg?imageMogr2/auto-orient/strip|imageView2/1/w/360/h/240"
        },
        {
            "id":8,
            "title": "张爱玲经典语录",
            "desc": "1、世上有用的人往往都是俗人。 2、正经女人虽然痛恨荡妇，其实若有机会 扮个妖妇角色的话，没有一个不跃跃欲试的。 3、完美的女人比完美的男人更完...",
            "imgUrl": " https://upload-images.jianshu.io/upload_images/16572117-9777cb5c4c862d71.jpg?imageMogr2/auto-orient/strip|imageView2/1/w/360/h/240"
        },
        {
            "id":9,
            "title": "张爱玲经典语录",
            "desc": "1、世上有用的人往往都是俗人。 2、正经女人虽然痛恨荡妇，其实若有机会 扮个妖妇角色的话，没有一个不跃跃欲试的。 3、完美的女人比完美的男人更完...",
            "imgUrl": " https://upload-images.jianshu.io/upload_images/16572117-9777cb5c4c862d71.jpg?imageMogr2/auto-orient/strip|imageView2/1/w/360/h/240"
        },{
            "id":10,
            "title": "张爱玲经典语录",
            "desc": "1、世上有用的人往往都是俗人。 2、正经女人虽然痛恨荡妇，其实若有机会 扮个妖妇角色的话，没有一个不跃跃欲试的。 3、完美的女人比完美的男人更完...",
            "imgUrl": " https://upload-images.jianshu.io/upload_images/16572117-9777cb5c4c862d71.jpg?imageMogr2/auto-orient/strip|imageView2/1/w/360/h/240"
        },{
            "id":11,
            "title": "张爱玲经典语录",
            "desc": "1、世上有用的人往往都是俗人。 2、正经女人虽然痛恨荡妇，其实若有机会 扮个妖妇角色的话，没有一个不跃跃欲试的。 3、完美的女人比完美的男人更完...",
            "imgUrl": " https://upload-images.jianshu.io/upload_images/16572117-9777cb5c4c862d71.jpg?imageMogr2/auto-orient/strip|imageView2/1/w/360/h/240"
        }
] 
}